las.py
las-0.0.5.dist-info/METADATA
las-0.0.5.dist-info/WHEEL
las-0.0.5.dist-info/top_level.txt
las-0.0.5.dist-info/RECORD
