Metadata-Version: 2.1
Name: las
Version: 0.0.5
Summary: A reader for Canadian Well Logging Society LAS (Log ASCII Standard) files.
Home-page: https://github.com/WarrenWeckesser/las
Author: Warren Weckesser
License: BSD
Classifier: License :: OSI Approved :: BSD License
Classifier: Intended Audience :: Developers
Classifier: Operating System :: OS Independent
Classifier: Programming Language :: Python :: 3
Classifier: Programming Language :: Python :: 3.7
Classifier: Programming Language :: Python :: 3.8
Classifier: Programming Language :: Python :: 3.9
Classifier: Programming Language :: Python :: 3.10
Classifier: Programming Language :: Python :: 3.11
Classifier: Programming Language :: Python :: 3.12
Requires-Dist: numpy >=1.5.0
